MANIFEST.in
setup.cfg
setup.py
django_frontflow.egg-info/PKG-INFO
django_frontflow.egg-info/SOURCES.txt
django_frontflow.egg-info/dependency_links.txt
django_frontflow.egg-info/pbr.json
django_frontflow.egg-info/top_level.txt
frontflow/__init__.py
frontflow/front-template/.gitignore
frontflow/front-template/Gruntfile.coffee
frontflow/front-template/package.json
frontflow/front-template/src/coffee/.gitkeep
frontflow/front-template/src/less/.gitkeep
frontflow/front-template/src/sass/.gitkeep
frontflow/management/__init__.py
frontflow/management/commands/__init__.py
frontflow/management/commands/front.py