Metadata-Version: 1.1
Name: django-frontflow
Version: 0.0.3
Summary: Grunt based frontend asset management utils
Home-page: https://github.com/Unholster/django-frontflow
Author: Sebastián Acuña
Author-email: sacuna@gmail.com
License: MIT
Download-URL: https://github.com/Unholster/django-frontflow/tarball/0.0.1
Platform: UNKNOWN
